LICENSE
MANIFEST.in
README.md
setup.py
django_materialize_forms.egg-info/PKG-INFO
django_materialize_forms.egg-info/SOURCES.txt
django_materialize_forms.egg-info/dependency_links.txt
django_materialize_forms.egg-info/top_level.txt
materialize_forms/__init__.py
materialize_forms/admin.py
materialize_forms/models.py
materialize_forms/tests.py
materialize_forms/views.py
materialize_forms/static/css/materialize.css
materialize_forms/static/css/materialize.min.css
materialize_forms/static/font/material-design-icons/LICENSE.txt
materialize_forms/static/font/material-design-icons/Material-Design-Icons.eot
materialize_forms/static/font/material-design-icons/Material-Design-Icons.svg
materialize_forms/static/font/material-design-icons/Material-Design-Icons.ttf
materialize_forms/static/font/material-design-icons/Material-Design-Icons.woff
materialize_forms/static/font/material-design-icons/Material-Design-Icons.woff2
materialize_forms/static/font/roboto/Roboto-Bold.ttf
materialize_forms/static/font/roboto/Roboto-Bold.woff
materialize_forms/static/font/roboto/Roboto-Bold.woff2
materialize_forms/static/font/roboto/Roboto-Light.ttf
materialize_forms/static/font/roboto/Roboto-Light.woff
materialize_forms/static/font/roboto/Roboto-Light.woff2
materialize_forms/static/font/roboto/Roboto-Medium.ttf
materialize_forms/static/font/roboto/Roboto-Medium.woff
materialize_forms/static/font/roboto/Roboto-Medium.woff2
materialize_forms/static/font/roboto/Roboto-Regular.ttf
materialize_forms/static/font/roboto/Roboto-Regular.woff
materialize_forms/static/font/roboto/Roboto-Regular.woff2
materialize_forms/static/font/roboto/Roboto-Thin.ttf
materialize_forms/static/font/roboto/Roboto-Thin.woff
materialize_forms/static/font/roboto/Roboto-Thin.woff2
materialize_forms/static/js/materialize.js
materialize_forms/static/js/materialize.min.js
materialize_forms/templates/materialize/field.html
materialize_forms/templates/materialize/field_choices.html
materialize_forms/templates/materialize/field_errors.html
materialize_forms/templates/materialize/field_help.html
materialize_forms/templates/materialize/field_visible.html
materialize_forms/templatetags/__init__.py
