Metadata-Version: 1.1
Name: django-materialize-forms
Version: 0.2.0
Summary: Materializecss support for Django projects
Home-page: https://github.com/zokis/django-materialize-forms
Author: Marcelo Fonseca Tambalo
Author-email: marcelo.zokis@gmail.com
License: MIT
Platform: UNKNOWN
Classifier: Development Status :: 5 - Production/Stable
Classifier: Intended Audience :: Developers
Classifier: Programming Language :: Python
Classifier: Operating System :: OS Independent
Classifier: Topic :: Software Development :: Libraries
Classifier: Topic :: Utilities
Classifier: Environment :: Web Environment
Classifier: Framework :: Django
